{
  "action": {
    "description": "Senate Comm - Favorable Recommendation [Senate Judiciary, Law Enforcement, and Criminal Justice Committee]",
    "occurred_at": "2026-02-26T16:25:11+00:00",
    "jurisdiction_id": "~{\"classification\": \"upper\"}",
    "session_id": "2026",
    "entity_type": "bill",
    "classifications": [
      "committee-passage-favorable"
    ],
    "related_entities": [
      {
        "name": "Judiciary, Law Enforcement, and Criminal Justice",
        "entity_type": "organization",
        "organization_id": null
      }
    ],
    "sources": [
      {
        "url": "https://le.utah.gov/~2026/bills/static/HB0205.html",
        "note": ""
      }
    ]
  },
  "bill_id": "HB 205"
}